fighub/__init__.py
fighub/colors.py
fighub/draw.py
fighub/marker.py
fighub/paras_latex.py
fighub-0.1.6.dist-info/METADATA
fighub-0.1.6.dist-info/WHEEL
fighub-0.1.6.dist-info/RECORD
