Metadata-Version: 2.4
Name: fighub
Version: 0.1.6
Summary: A simple example package for draw
Author-email: Junshan Yin <junshanyin@163.com>
Requires-Dist: matplotlib-inline==0.1.7
Requires-Dist: matplotlib==3.10.3
Requires-Dist: numpy==2.2.6
